kzstack/KZStack.py
kzstack/__init__.py
kzstack-1.0.4.dist-info/METADATA
kzstack-1.0.4.dist-info/WHEEL
kzstack-1.0.4.dist-info/top_level.txt
kzstack-1.0.4.dist-info/RECORD
