Metadata-Version: 2.4
Name: kzstack
Version: 1.0.4
Summary: a package to stack images for many purposes
Author: Kevin Zhu
Author-email: kzhu2099@gmail.com
Maintainer: Kevin Zhu
Maintainer-email: kzhu2099@gmail.com
License: MIT License
Project-URL: Homepage, https://github.com/kzhu2099/KZ-Stack
Project-URL: Issues, https://github.com/kzhu2099/KZ-Stack/issues
Classifier: Development Status :: 5 - Production/Stable
Classifier: Intended Audience :: Developers
Classifier: Intended Audience :: End Users/Desktop
Classifier: License :: OSI Approved :: MIT License
Classifier: Natural Language :: English
Classifier: Operating System :: OS Independent
Classifier: Programming Language :: Python :: 3
Requires-Python: >=3.9
